helpful_django/__init__.py
helpful_django/manage.py
helpful_django/settings.py
helpful_django/apps/__init__.py
helpful_django/apps/pastebin/__init__.py
helpful_django/apps/pastebin/pastebin/__init__.py
helpful_django/apps/pastebin/pastebin/admin.py
helpful_django/apps/pastebin/pastebin/apps.py
helpful_django/apps/pastebin/pastebin/forms.py
helpful_django/apps/pastebin/pastebin/models.py
helpful_django/apps/pastebin/pastebin/tests.py
helpful_django/apps/pastebin/pastebin/urls.py
helpful_django/apps/pastebin/pastebin/views.py
helpful_django/apps/pastebin/pastebin/migrations/0001_initial.py
helpful_django/apps/pastebin/pastebin/migrations/__init__.py
helpful_django/templates/pastebin/create.html
helpful_django/templates/pastebin/view.html
helpful_django/templates/pastebin/status/deleted.html
helpful_django/templates/pastebin/status/not_found.html
helpful_django/utils/__init__.py
helpful_django/utils/administrative.py
helpful_django/utils/errors.py
helpful_django-0.8.11.dist-info/LICENSE
helpful_django-0.8.11.dist-info/METADATA
helpful_django-0.8.11.dist-info/WHEEL
helpful_django-0.8.11.dist-info/entry_points.txt
helpful_django-0.8.11.dist-info/top_level.txt
helpful_django-0.8.11.dist-info/RECORD
